arunpyutils/__init__.py
arunpyutils/pyutils.py
arunpyutils-0.0.1.dist-info/METADATA
arunpyutils-0.0.1.dist-info/WHEEL
arunpyutils-0.0.1.dist-info/top_level.txt
arunpyutils-0.0.1.dist-info/RECORD
